django_yugabytedb/__init__.py
django_yugabytedb/base.py
django_yugabytedb/client.py
django_yugabytedb/creation.py
django_yugabytedb/features.py
django_yugabytedb/introspection.py
django_yugabytedb/operations.py
django_yugabytedb/schema.py
django_yugabytedb-4.2.0.1.dist-info/LICENSE
django_yugabytedb-4.2.0.1.dist-info/METADATA
django_yugabytedb-4.2.0.1.dist-info/WHEEL
django_yugabytedb-4.2.0.1.dist-info/top_level.txt
django_yugabytedb-4.2.0.1.dist-info/RECORD
