Metadata-Version: 2.1
Name: django-yugabytedb
Version: 4.2.0.1
Summary: Django backend for YugabyteDB
Home-page: https://www.yugabyte.com/
Author: Yugabyte
Author-email: hbhanawat@yugabyte.com
Maintainer: Sfurti Sarah
Maintainer-email: ssarah@yugabyte.com
License: Apache
Project-URL: Documentation, https://docs.yugabyte.com/
Project-URL: Code, https://github.com/yugabyte/yb-django
Classifier: Development Status :: 5 - Production/Stable
Classifier: Environment :: Web Environment
Classifier: Framework :: Django
Classifier: Framework :: Django :: 3.2
Classifier: Framework :: Django :: 4.0
Classifier: Intended Audience :: Developers
Classifier: Operating System :: OS Independent
Classifier: Programming Language :: Python :: 3.8
Classifier: Programming Language :: Python :: 3.9
Classifier: Topic :: Internet :: WWW/HTTP
Classifier: Topic :: Internet :: WWW/HTTP :: Dynamic Content
Classifier: Topic :: Internet :: WWW/HTTP :: WSGI
Classifier: Topic :: Software Development :: Libraries :: Application Frameworks
Classifier: Topic :: Software Development :: Libraries :: Python Modules
Requires-Python: >=3.8
License-File: LICENSE
